temppython/__init__.py
temppython/myfunctions.py
temppython-0.1.0.dist-info/LICENSE.txt
temppython-0.1.0.dist-info/METADATA
temppython-0.1.0.dist-info/WHEEL
temppython-0.1.0.dist-info/top_level.txt
temppython-0.1.0.dist-info/RECORD
