Metadata-Version: 2.1
Name: temppython
Version: 0.1.0
Summary: First Python Library
Home-page: https://github.com/vivek-lakhataria/Python-Sample-Library
Author: AlpsInfoITSolution
Author-email: vivek.lakhataria@alpsinfo.net
License: UNKNOWN
Keywords: Library
Platform: UNKNOWN
Classifier: Development Status :: 3 - Alpha
Classifier: Intended Audience :: Developers
Classifier: Topic :: Software Development :: Build Tools
Classifier: License :: OSI Approved :: MIT License
Classifier: Programming Language :: Python
Classifier: Programming Language :: Python :: 3
Classifier: Programming Language :: Python :: 3.7
Classifier: Programming Language :: Python :: 3.8
Classifier: Programming Language :: Python :: 3.9
Classifier: Programming Language :: Python :: 3.10
Requires-Python: >=3.7
License-File: LICENSE.txt
Requires-Dist: numpy
Requires-Dist: scrapeasy
